OnePagePPT_43_LSC/onepagePPT_43.py
OnePagePPT43_LSC-0.0.1.dist-info/LICENSE.txt
OnePagePPT43_LSC-0.0.1.dist-info/METADATA
OnePagePPT43_LSC-0.0.1.dist-info/WHEEL
OnePagePPT43_LSC-0.0.1.dist-info/top_level.txt
OnePagePPT43_LSC-0.0.1.dist-info/RECORD
