Metadata-Version: 2.1
Name: OnePagePPT43-LSC
Version: 0.0.1
Summary: A python program that fills in formatted PPT
Author-email: Shicheng Lu <742466595@qq.com>
Project-URL: Homepage, https://www.baidu.com/
Project-URL: Bug Tracker, https://www.baidu.com/
Classifier: Programming Language :: Python :: 3
Classifier: License :: OSI Approved :: MIT License
Classifier: Operating System :: OS Independent
Requires-Python: >=3.7
License-File: LICENSE.txt
